acrl/__init__.py
acrl/agent.py
acrl/model.py
acrl/synthetic.py
acrl/utils.py
acrl-0.0.3.dist-info/LICENSE.md
acrl-0.0.3.dist-info/METADATA
acrl-0.0.3.dist-info/WHEEL
acrl-0.0.3.dist-info/top_level.txt
acrl-0.0.3.dist-info/RECORD
