Metadata-Version: 2.1
Name: acrl
Version: 0.0.3
Home-page: https://github.com/brilhana/almgren-chriss
Author: Alexandre Brilhante
Author-email: alexandre.brilhante@gmail.com
Project-URL: Bug Tracker, https://github.com/brilhana/almgren-chriss/issues
Classifier: Programming Language :: Python :: 3
Classifier: License :: OSI Approved :: MIT License
Classifier: Operating System :: OS Independent
Requires-Python: >=3.8
License-File: LICENSE.md
